{
  "KPIs": [
    {
      "title": "Average block time < 6.025s & maintain 10 validators",
      "description": "In order to have a reliable network, a KPI focusing on block production and validator stability is required. Timestamp of each block can be found using the block explorer (divided by 1000).",
      "reward": "100",
      "startDate": "20:05:2020 - 16:00 GMT",
      "measurementPeriod": "7 days",
      "annihilation": "Block finalization lags more than 600 blocks behind head at any point throughout the Measurement period",
      "successEvents": [
        "The difference between timestamps of block 910367 and block 1010749 must be less than 604,710,000 milliseconds",
        "Maintain a total of least 10 validators throughout the Measurement period"
      ],
      "endDate": "28:05:2020 - 16:00 GMT",
      "number": 1
    },
    {
      "title": "All proposals are cleared before they expire AND at no continuous 24h period are there 5 proposal in the active stage",
      "description": "For the governance process to work, all proposals must be dealt with professionally, and in reasonable time frame to avoiding blocking new proposals coming in.",
      "reward": "120",
      "measurementPeriod": "7 days",
      "startDate": "20/05/2020 - 16:00 GMT",
      "successEvents": [
        "No proposals expire due to missing votes",
        "At no point will the number of active proposal stay at 5 for longer than 14,400 blocks (~24h)",
        "For each new proposal, a forum post is opened for discussion between the council and other interested parties"
      ],
      "annihilation": "No malicious or unreasonable proposals are approved.",
      "endDate": "28/05/2020 - 16:00 GMT",
      "number": 2
    }
  ]
}
